{"000--34290rw03492jkd.000webhostapp.com":1,"0088system.xyz":1,"0219662.ro":1,"027.fyi":1,"0b57ha4k4zrd.top":1,"0delay.website":1,"0reddit.com":1,"0xz2-0934200-rt2.000webhostapp.com":1,"0xzr--yty67676767.000webhostapp.com":1,"10545200-100.000webhostapp.com":1,"11-88.000webhostapp.com":1,"2021-free-robux-generator.000webhostapp.com":1,"8phmgsh.0yrvtrh.com":1,"a9000-11848400.000webhostapp.com":1,"a9900-115446044.000webhostapp.com":1,"acoleakaze.000webhostapp.com":1,"adrianasite.000webhostapp.com":1,"afdafada.000webhostapp.com":1,"antony1212.000webhostapp.com":1,"asassawwrefrgrgxda.000webhostapp.com":1,"assistenzacontoristretto.000webhostapp.com":1,"back-flow.000webhostapp.com":1,"batrachian-bullets.000webhostapp.com":1,"bausond-paint.000webhostapp.com":1,"bddbdbfbfredfw.000webhostapp.com":1,"bgmistoreskins.000webhostapp.com":1,"blackig.000webhostapp.com":1,"bluebadgeinstgram.000webhostapp.com":1,"bullabhai.000webhostapp.com":1,"car-audios.000webhostapp.com":1,"centers4f3ty687v3r1f1c4t10nc0mf1rm4t10n.000webhostapp.com":1,"ceritanyabaru1221.000webhostapp.com":1,"comf1rm4t10nv3r1f1cat10ncent3rs1trp0rt.000webhostapp.com":1,"comf1rm4t10nv3r1f1cat10ncent3rs1trpo0rtt.000webhostapp.com":1,"content-ci360.01burda.com":1,"coordinated-tops.000webhostapp.com":1,"crabbed-toolboxes.000webhostapp.com":1,"demowlec.000webhostapp.com":1,"denemeaqdenemea.000webhostapp.com":1,"digitalprivati.000webhostapp.com":1,"discov050.000webhostapp.com":1,"ditriglyphic-glaze.000webhostapp.com":1,"dnxcwckrt8apt.000webhostapp.com":1,"esandashasmitha.000webhostapp.com":1,"fabo393.000webhostapp.com":1,"faceeb0o0o0k.000webhostapp.com":1,"fsfsfsegtrtttytyyt.000webhostapp.com":1,"fssffsgsgsg.000webhostapp.com":1,"ghyhtych.000webhostapp.com":1,"gruppointesa-2022.000webhostapp.com":1,"heigh-receptacle.000webhostapp.com":1,"helpfiledeskauth.000webhostapp.com":1,"hemistichal-deaths.000webhostapp.com":1,"hmonglearn.000webhostapp.com":1,"hoctaplinhtinh.000webhostapp.com":1,"icppp.000webhostapp.com":1,"imasitamk.000webhostapp.com":1,"inslagram-togin.000webhostapp.com":1,"instastoryjgadjdfjedhdhwdhfhfspfospfhospdhoph.000webhostapp.com":1,"instservice.000webhostapp.com":1,"itausolucoessss.000webhostapp.com":1,"joaxli-tame-dina548.000webhostapp.com":1,"kisshfm.000webhostapp.com":1,"latvianpuhlvs.000webhostapp.com":1,"lnstagramcentre.000webhostapp.com":1,"login.039304.com":1,"lojinharbala.000webhostapp.com":1,"ojdv7gcfmsfsgtz.000webhostapp.com":1,"onlineepay.000webhostapp.com":1,"osm.0x78.xyz":1,"ourcshost7867896.000webhostapp.com":1,"pannelloprivati.000webhostapp.com":1,"plhyox5hloojxf.000webhostapp.com":1,"produc-4355324234.000webhostapp.com":1,"pussyunlock.000webhostapp.com":1,"redirecionarads.000webhostapp.com":1,"revisionaconfigurazionebper.000webhostapp.com":1,"rohanratnala.000webhostapp.com":1,"rycovictorino.000webhostapp.com":1,"s.039304.com":1,"s4afety641c0mfii1rm4t10n32s44adss.000webhostapp.com":1,"s4fety641c0mf1rm4t10n32s4page3s5.000webhostapp.com":1,"securestaffaccess1.000webhostapp.com":1,"serviziosella.000webhostapp.com":1,"sfsffsgegrhhtrhtr.000webhostapp.com":1,"sfsfsfwfeegegq.000webhostapp.com":1,"sparkassede.000webhostapp.com":1,"stwskkqdksdy8k.000webhostapp.com":1,"sweetymoment.000webhostapp.com":1,"telasdotinho.000webhostapp.com":1,"thrombolytic-pipes.000webhostapp.com":1,"u5rfyjxo3lynj.000webhostapp.com":1,"unanalyzed-personal.000webhostapp.com":1,"unshrinking-studies.000webhostapp.com":1,"vppadmin.01article.com":1,"webhostbuilders-global201.000webhostapp.com":1,"webrp.000webhostapp.com":1,"www.07172021.com":1,"www.go-eki-co.popend.jp.021shunfu.com.cn":1,"www.legolok-com.0715.tw":1,"zkkbk98.000webhostapp.com":1,"005582.vip":1,"005583.vip":1,"005584.vip":1,"005585.vip":1,"005586.vip":1,"005587.vip":1,"005589.vip":1,"0099.io":1,"00mmd.com":1,"00nba-zkbw.000webhostapp.com":1,"01color.com":1,"023web.com":1,"0265331.com":1,"027gay.cn":1,"02sport.com":1,"035alerts-online-micro.062importados.com":1,"040budget.host":1,"0431gay.cn":1,"0551gay.cn":1,"075computerservice.nl":1,"08uxmg2bz7hc.top":1,"0a8d87mlbcac.top":1,"0pen-spotify.info":1,"0pen.online":1,"0rionfcu.com":1,"0s.click":1,"11504200-02.000webhostapp.com":1,"190304012-00.000webhostapp.com":1,"3333009-00.000webhostapp.com":1,"83197-62.000webhostapp.com":1,"896040611-00.000webhostapp.com":1,"aa15000-page.000webhostapp.com":1,"ab15000-page.000webhostapp.com":1,"accenturehh.000webhostapp.com":1,"accessoclientigruppointesamobile.000webhostapp.com":1,"agewhwshweeh.000webhostapp.com":1,"ajudawebbgrave.000webhostapp.com":1,"alwtpofohv6jpu.000webhostapp.com":1,"amamalpa.000webhostapp.com":1,"artelhwidpaioy.000webhostapp.com":1,"asaasdwdwwdfeeffe.000webhostapp.com":1,"att-verfylog-in00.000webhostapp.com":1,"authboncoin.000webhostapp.com":1,"authelia.0bdd.de":1,"axwefduis.000webhostapp.com":1,"b5mfpvrnsfvmz.000webhostapp.com":1,"bdfhrfax.000webhostapp.com":1,"bookable-specializa.000webhostapp.com":1,"bunted-feeds.000webhostapp.com":1,"c0mf1r240-s4f3tyw3b954.000webhostapp.com":1,"cancontest.000webhostapp.com":1,"cardcreditonupagamentos.000webhostapp.com":1,"celudstore.000webhostapp.com":1,"compilabloccoportale.000webhostapp.com":1,"connectmyweb1.000webhostapp.com":1,"construisonsdansunmondequibouge.000webhostapp.com":1,"cult1v4t10n-3xp4ns10n.000webhostapp.com":1,"cyh7rfeabkqaodv.000webhostapp.com":1,"diabolusink.000webhostapp.com":1,"djtddmbya7xoj.000webhostapp.com":1,"eftrenet.000webhostapp.com":1,"egegeeggewdwqw.000webhostapp.com":1,"fgffghtthhrer.000webhostapp.com":1,"fsfsfswwwwaaaaa.000webhostapp.com":1,"fsfssffsqwqqqq.000webhostapp.com":1,"fssfsfwweefergrg.000webhostapp.com":1,"furany6uqr43apfd.000webhostapp.com":1,"g675.000webhostapp.com":1,"geegegrrrrtrtrt.000webhostapp.com":1,"ghostmoodhood999.000webhostapp.com":1,"golemgreat122.000webhostapp.com":1,"goofoo77786.000webhostapp.com":1,"govnance.000webhostapp.com":1,"group-invited.000webhostapp.com":1,"gruppobper-aggiornamentodati.000webhostapp.com":1,"gyr6taahzqa1zdx65ltn.000webhostapp.com":1,"hilalprojeck.000webhostapp.com":1,"hrhrrhhrhreef.000webhostapp.com":1,"hrrhrhhrttjtj.000webhostapp.com":1,"htrhyththgtu123.000webhostapp.com":1,"imd-invoice.0bdd.de":1,"infohomework10101.000webhostapp.com":1,"jackcolen231.000webhostapp.com":1,"jnyv5doho8wxe.000webhostapp.com":1,"johnson252.000webhostapp.com":1,"kjilod.000webhostapp.com":1,"kkpaham35789.000webhostapp.com":1,"konsrtiiuty.000webhostapp.com":1,"labyrinthian-instru.000webhostapp.com":1,"licencias-federales-com-mx.000webhotsapp.com":1,"llinfoo.000webhostapp.com":1,"localizzaportaleweb.000webhostapp.com":1,"login.071614.com":1,"login.0uth.com":1,"marcadatest.000webhostapp.com":1,"meta-suppport-security.000webhostapp.com":1,"mobile-de-details-191004913.000webhostapp.com":1,"moddeeeuiewuiwehew.000webhostapp.com":1,"mongrel-indexes.000webhostapp.com":1,"morsalinhossen.000webhostapp.com":1,"narutoccsfake.000webhostapp.com":1,"nb2023.000webhostapp.com":1,"nedbnkverrification.000webhostapp.com":1,"noismrcadolirba.000webhostapp.com":1,"nossorenner.000webhostapp.com":1,"nu-atualizar-infor.000webhostapp.com":1,"olouwae45.000webhostapp.com":1,"owa-documents.000webhostapp.com":1,"parasuaempresa.000webhostapp.com":1,"photometric-firer.000webhostapp.com":1,"picssxsx.000webhostapp.com":1,"pitihlahhabis.000webhostapp.com":1,"portaratest.000webhostapp.com":1,"postalfrancecompte.000webhostapp.com":1,"postcanada-canadaposte.0user.info":1,"pr0c33d1ng-t3xtur3.000webhostapp.com":1,"pr3c1nct-l4tt1c3w0rk.000webhostapp.com":1,"propaganda-threader.000webhostapp.com":1,"pspapas.000webhostapp.com":1,"pucallpaconocida2111.000webhostapp.com":1,"pucallpaconocidaa00conocida000.000webhostapp.com":1,"pucallpaconocidaa0conocida.000webhostapp.com":1,"pucallpaconocidaaa22444.000webhostapp.com":1,"pucallpaconocidatikconocida00.000webhostapp.com":1,"pucallpinaconocida000conoscapucallpa.000webhostapp.com":1,"pucallpinaconocida4344.000webhostapp.com":1,"ramebana98.000webhostapp.com":1,"rastreio-de-compraspediuchegou-entregas541.000webhostapp.com":1,"rebokemisuk.000webhostapp.com":1,"reippuwjcw1yybh2.000webhostapp.com":1,"relay.0svc.com":1,"reportegrupal12.000webhostapp.com":1,"revisionemanuale.000webhostapp.com":1,"rtjnylpuquilvn85.000webhostapp.com":1,"s4fety641c0mf1rm4t10n32s4page3s.000webhostapp.com":1,"sdlmgkkgngfg87.000webhostapp.com":1,"sfsfssfwwwqaaass.000webhostapp.com":1,"silimandgte.000webhostapp.com":1,"silimanviral.000webhostapp.com":1,"slgnln-att-dynamic-iamlrr-lrrcontroller.000webhostapp.com":1,"suportespringfy.000webhostapp.com":1,"tdcustomteam.000webhostapp.com":1,"technikboerse-com-details-240919512.000webhostapp.com":1,"testingports.000webhostapp.com":1,"undesirous-costs.000webhostapp.com":1,"urangkurang88.000webhostapp.com":1,"utvortmcinbhbf.000webhostapp.com":1,"walletconnectcentre.000webhostapp.com":1,"wey56.000webhostapp.com":1,"www.0800asbestos.com":1,"www.0ffset.net":1,"www.0xfrog.com":1,"www.virtualcall.com.br.0800voip.com.br":1,"ycimail.000webhostapp.com":1,"yi7q26ngpzhtc5v.000webhostapp.com":1,"youtrack.0x.at":1,"ze8games.000webhostapp.com":1,"zfdniina7iqljpbbar.000webhostapp.com":1,"zumrnz.000webhostapp.com":1,"000343594567126312342754pgsbsnsswrng.000webhostapp.com":1,"011shop.rs":1,"087558.com":1,"08bb1fn3t4.com":1,"0ffice365support.online":1,"0nlinebanc0promericagt-accesos.online":1,"0xtitans.com":1,"0yenreform.site":1,"110088900-a4000.000webhostapp.com":1,"115480400123.000webhostapp.com":1,"1511054800.000webhostapp.com":1,"1gbbwuj32hwxig.000webhostapp.com":1,"3pqj85t6mkf2vqs.000webhostapp.com":1,"4ch4d0.000webhostapp.com":1,"546986565-00.000webhostapp.com":1,"7006521478569-86.000webhostapp.com":1,"a2023sks-02-page.000webhostapp.com":1,"a2023sks-03-page.000webhostapp.com":1,"aadcdn.secure.office.0erty.com":1,"aadcdnn.secure.office.0erty.com":1,"absu-media.000webhostapp.com":1,"absutrendz.000webhostapp.com":1,"acessoviasrdsland.000webhostapp.com":1,"air-mail-keywords.000webhostapp.com":1,"app-sospesa.000webhostapp.com":1,"appr3c0psersteradsv3r1f1c4ti0nc0mf1rm4t10n.000webhostapp.com":1,"appr3c0psersteradsv3rific4ti0nc0mf1rm4tion.000webhostapp.com":1,"areaprivataweb2022.000webhostapp.com":1,"babaevipviptt.000webhostapp.com":1,"berijalannauk.000webhostapp.com":1,"bgmireward2021.000webhostapp.com":1,"bnakakakaaka.000webhostapp.com":1,"butterfactory.000webhostapp.com":1,"camellolunar.000webhostapp.com":1,"casosdelavidareal.000webhostapp.com":1,"ccccbokepramadan.000webhostapp.com":1,"cent3rs4f3ty67v3rific4ti0nc0mf1rm4t10n.000webhostapp.com":1,"centers4f3ty67vreiffic4ti0nc0mf1rm4t10n.000webhostapp.com":1,"certificadispositivo23.000webhostapp.com":1,"chm6ly9hdhqte.000webhostapp.com":1,"chunmacorp.000webhostapp.com":1,"clienterefunnels.02o.co":1,"cmewpkjesamzz2.000webhostapp.com":1,"comf1rm4tt10nv3r1f1cat10ncent3rs1ttrpo0rt.000webhostapp.com":1,"couthy-lots.000webhostapp.com":1,"croteiankus.000webhostapp.com":1,"cufic-inspection.000webhostapp.com":1,"cultklbeauty.000webhostapp.com":1,"dadafafwqqfwwg.000webhostapp.com":1,"derryjulianuk.000webhostapp.com":1,"dfdfeererqwfbnnnnn.000webhostapp.com":1,"dgdgdgehdehhe.000webhostapp.com":1,"dhrtherre.000webhostapp.com":1,"dioseshahaputs.000webhostapp.com":1,"directlierfluxfo.000webhostapp.com":1,"djcjninciencnernevnruevnruvn.000webhostapp.com":1,"docs.028426.com":1,"dragoncity28.000webhostapp.com":1,"dzhdrhdrhdr.000webhostapp.com":1,"egegegeghrrhhr.000webhostapp.com":1,"eserverurl.000webhostapp.com":1,"event00reward.000webhostapp.com":1,"exterminatorsofficial.000webhostapp.com":1,"fandecck.000webhostapp.com":1,"fb666.000webhostapp.com":1,"fbtest4.000webhostapp.com":1,"fdfdfdrggrhrhr.000webhostapp.com":1,"fewgerddsg.000webhostapp.com":1,"fggfgffghghgrr.000webhostapp.com":1,"fgjtsvvvv.000webhostapp.com":1,"fhfhfhrtjjtrjr.000webhostapp.com":1,"fhgfhfhtwqwsrg.000webhostapp.com":1,"floreated-searchlig.000webhostapp.com":1,"freenet99.000webhostapp.com":1,"freeskinxsuitbgmi.000webhostapp.com":1,"freeultrakill.000webhostapp.com":1,"fsfsfsfeeggeehrhr.000webhostapp.com":1,"fwwffwfwegegeg.000webhostapp.com":1,"galsecus-galsiaonlisnes-ports.000webhostapp.com":1,"gdddgeggerhthj.000webhostapp.com":1,"geeggehrrhrhe.000webhostapp.com":1,"gfgfgfhghghguy.000webhostapp.com":1,"gfvucunamem6.000webhostapp.com":1,"ghourcof97.000webhostapp.com":1,"gm1ayry6jdaf2.000webhostapp.com":1,"guy7kinjd3pi5.000webhostapp.com":1,"harbeebiyfootwear.000webhostapp.com":1,"hayeantukak.000webhostapp.com":1,"hayneung.000webhostapp.com":1,"hffhhfjttjttjtr.000webhostapp.com":1,"htikwlzerew81.000webhostapp.com":1,"iawn1fka4mpshnm.000webhostapp.com":1,"impressible-latch.000webhostapp.com":1,"instancepaiement500507.000webhostapp.com":1,"instasecurityline.000webhostapp.com":1,"itau-card-oficial.000webhostapp.com":1,"jirkxour63k2ap.000webhostapp.com":1,"kkookijuuyhytgftg.000webhostapp.com":1,"kodrtaukys.000webhostapp.com":1,"ksp-sb-com.000webhostapp.com":1,"kukiluyyujtk.000webhostapp.com":1,"mail.04d.co":1,"meta-suupport-infoo.000webhostapp.com":1,"modfullcrackop.000webhostapp.com":1,"mtmkcrw5vnnv.000webhostapp.com":1,"octachordal-pools.000webhostapp.com":1,"ofertas-ltaucard-online.000webhostapp.com":1,"okokkouhuhygtfrtd.000webhostapp.com":1,"okokkuhuhuiiu.000webhostapp.com":1,"ooooooooooooooooooooooooooo-ooo.000webhostapp.com":1,"op.0ps.us":1,"ozz-account.000webhostapp.com":1,"p-type-pecks.000webhostapp.com":1,"p2pathnpa-ypal.000webhostapp.com":1,"paypal.0101.cl":1,"pcypell.000webhostapp.com":1,"pelagian-marines.000webhostapp.com":1,"pescadofalso777.000webhostapp.com":1,"podgrab.0124816.xyz":1,"politicalscienceproject7.000webhostapp.com":1,"posteidentificazione-info.000webhostapp.com":1,"ppinfolive.000webhostapp.com":1,"proketcikolitr.000webhostapp.com":1,"qb8uv3irpb3yrg42k.000webhostapp.com":1,"quk6nkmllgzngm.000webhostapp.com":1,"r3d1r3ct-4cc3ss1ng.000webhostapp.com":1,"raftxsalhot.000webhostapp.com":1,"reservaequipof.000webhostapp.com":1,"reservaequiposdy.000webhostapp.com":1,"restryuct.000webhostapp.com":1,"reunionistic-compen.000webhostapp.com":1,"rockettenis.000webhostapp.com":1,"s4f3ty984-us3rs045.000webhostapp.com":1,"samisoooo.000webhostapp.com":1,"saraaly.000webhostapp.com":1,"scban.000webhostapp.com":1,"scottexinvestment.000webhostapp.com":1,"sexxphotoss1.000webhostapp.com":1,"sffsfsegegeg.000webhostapp.com":1,"sfsffsegegeheh.000webhostapp.com":1,"sfsffsfsgeegegh.000webhostapp.com":1,"sfsfsfaqdwegrdwdvbzz.000webhostapp.com":1,"sfsfsfsfgsgswswws.000webhostapp.com":1,"sgawon66543.000webhostapp.com":1,"skuyzzzzazza.000webhostapp.com":1,"srqnhk7lrmgb.000webhostapp.com":1,"subuhpagirecoveryrec.000webhostapp.com":1,"sucursalpersonastransacc.000webhostapp.com":1,"sucursalvirtualpostovon.000webhostapp.com":1,"tharnamelease.000webhostapp.com":1,"tigeroot.000webhostapp.com":1,"tonsillitic-refurbi.000webhostapp.com":1,"tottalasdfsadfwfrgsdfgsdfgsdfgadfgadfg.000webhostapp.com":1,"unburnt-allowance.000webhostapp.com":1,"v3r1f1c4t3d01-p4g3s1t3.000webhostapp.com":1,"vrl2s1tpuhm3ux.000webhostapp.com":1,"w8milonteam.000webhostapp.com":1,"watspp09.000webhostapp.com":1,"webpbynaufal.000webhostapp.com":1,"www.clienterefunnels.02o.co":1,"www.paypal.0101.cl":1,"xvmail.000webhostapp.com":1,"yuts1.000webhostapp.com":1,"zzkbbnnk24.000webhostapp.com":1,"0xfe.pl":1,"14356000.000webhostapp.com":1,"7qh6gbecw7pbcc1a8.000webhostapp.com":1,"ad0be0ffice.000webhostapp.com":1,"betcoupon.000webhostapp.com":1,"binhchonfbngaymoi.000webhostapp.com":1,"discov025.000webhostapp.com":1,"extelase.000webhostapp.com":1,"faccebooksesion.000webhostapp.com":1,"facelibroo.000webhostapp.com":1,"gfgffhghgyj.000webhostapp.com":1,"groupo-sex.000webhostapp.com":1,"in-e-mail-in.000webhostapp.com":1,"in-user-help-code.000webhostapp.com":1,"instegram-4685.000webhostapp.com":1,"login.028426.com":1,"nhankimcuong645.000webhostapp.com":1,"nlbcustomerservicecentre.000webhostapp.com":1,"payviabelgiquepal.000webhostapp.com":1,"provincia11.000webhostapp.com":1,"provincia5.000webhostapp.com":1,"redirectby.000webhostapp.com":1,"rhrrhhrhrrh.000webhostapp.com":1,"shoppingonline2.000webhostapp.com":1,"skuyyykiwwwyaw.000webhostapp.com":1,"snapchaatie.000webhostapp.com":1,"telegrammatic-drive.000webhostapp.com":1,"tiktok-123.000webhostapp.com":1,"unchanged-slash.000webhostapp.com":1,"vacation.069556.com":1,"versioneweb-sicurezza.000webhostapp.com":1,"vprovi.000webhostapp.com":1,"wedsteria.000webhostapp.com":1,"wingetonlinehelper.000webhostapp.com":1,"www.0114sl.com":1,"www.helpdesk.0717.co.za":1}